docs/conf.py
docs/utils.py
docs/write_redirects.py
ibm_watsonx_ai/Set.py
ibm_watsonx_ai/__init__.py
ibm_watsonx_ai/ai_services.py
ibm_watsonx_ai/assets.py
ibm_watsonx_ai/client.py
ibm_watsonx_ai/connections.py
ibm_watsonx_ai/credentials.py
ibm_watsonx_ai/deployments.py
ibm_watsonx_ai/experiments.py
ibm_watsonx_ai/export_assets.py
ibm_watsonx_ai/factsheets.py
ibm_watsonx_ai/folder_assets.py
ibm_watsonx_ai/foundation_models_manager.py
ibm_watsonx_ai/functions.py
ibm_watsonx_ai/hpo.py
ibm_watsonx_ai/href_definitions.py
ibm_watsonx_ai/hw_spec.py
ibm_watsonx_ai/import_assets.py
ibm_watsonx_ai/lifecycle.py
ibm_watsonx_ai/metanames.py
ibm_watsonx_ai/model_definition.py
ibm_watsonx_ai/models.py
ibm_watsonx_ai/parameter_sets.py
ibm_watsonx_ai/pipelines.py
ibm_watsonx_ai/pkg_extn.py
ibm_watsonx_ai/projects.py
ibm_watsonx_ai/repository.py
ibm_watsonx_ai/runtime_definitions.py
ibm_watsonx_ai/script.py
ibm_watsonx_ai/service_instance.py
ibm_watsonx_ai/shiny.py
ibm_watsonx_ai/spaces.py
ibm_watsonx_ai/sw_spec.py
ibm_watsonx_ai/task_credentials.py
ibm_watsonx_ai/training.py
ibm_watsonx_ai/trashed_assets.py
ibm_watsonx_ai/volumes.py
ibm_watsonx_ai/wml_client_error.py
ibm_watsonx_ai/wml_resource.py
ibm_watsonx_ai/_wrappers/__init__.py
ibm_watsonx_ai/_wrappers/requests.py
ibm_watsonx_ai/data_loaders/__init__.py
ibm_watsonx_ai/data_loaders/experiment.py
ibm_watsonx_ai/data_loaders/text_loader.py
ibm_watsonx_ai/data_loaders/datasets/__init__.py
ibm_watsonx_ai/data_loaders/datasets/base_documents.py
ibm_watsonx_ai/data_loaders/datasets/constants.py
ibm_watsonx_ai/data_loaders/datasets/documents.py
ibm_watsonx_ai/data_loaders/datasets/experiment.py
ibm_watsonx_ai/data_loaders/datasets/tabular.py
ibm_watsonx_ai/data_loaders/datasets/tabular_documents.py
ibm_watsonx_ai/deployment/__init__.py
ibm_watsonx_ai/deployment/base_deployment.py
ibm_watsonx_ai/deployment/batch.py
ibm_watsonx_ai/deployment/web_service.py
ibm_watsonx_ai/experiment/__init__.py
ibm_watsonx_ai-1.4.11.dist-info/METADATA
ibm_watsonx_ai-1.4.11.dist-info/WHEEL
ibm_watsonx_ai-1.4.11.dist-info/top_level.txt
ibm_watsonx_ai-1.4.11.dist-info/RECORD
