Metadata-Version: 2.4
Name: ibm_watsonx_ai
Version: 1.4.11
Summary: IBM watsonx.ai API Client
Author: IBM
Maintainer-email: Łukasz Ćmielowski <lukasz.cmielowski@pl.ibm.com>, Dorota Lączak <dorota.laczak@ibm.com>
License: BSD-3-Clause
Project-URL: Homepage, https://ibm.github.io/watsonx-ai-python-sdk
Keywords: watsonx.ai,machine learning,IBM,Bluemix,client,API,IBM Cloud
Classifier: Development Status :: 5 - Production/Stable
Classifier: Natural Language :: English
Classifier: License :: OSI Approved :: BSD License
Classifier: Programming Language :: Python :: 3.10
Classifier: Programming Language :: Python :: 3.11
Classifier: Programming Language :: Python :: 3.12
Classifier: Programming Language :: Python :: 3.13
Classifier: Operating System :: MacOS :: MacOS X
Classifier: Operating System :: POSIX :: Linux
Classifier: Operating System :: Microsoft :: Windows
Classifier: Intended Audience :: Science/Research
Classifier: Intended Audience :: Developers
Classifier: Intended Audience :: Information Technology
Classifier: Topic :: Software Development :: Libraries
Classifier: Topic :: Software Development :: Libraries :: Python Modules
Classifier: Topic :: Scientific/Engineering :: Artificial Intelligence
Classifier: Topic :: Scientific/Engineering :: Information Analysis
Classifier: Topic :: Internet
Requires-Python: <3.14,>=3.11
Requires-Dist: requests
Requires-Dist: httpx<0.29,>=0.27
Requires-Dist: urllib3
Requires-Dist: pandas<2.3.0,>=0.24.2
Requires-Dist: certifi
Requires-Dist: lomond
Requires-Dist: tabulate
Requires-Dist: packaging
Requires-Dist: ibm-cos-sdk<2.15.0,>=2.12.0
Requires-Dist: cachetools
Provides-Extra: rag
Requires-Dist: langchain-core<0.4,>=0.3.80; extra == "rag"
Requires-Dist: langchain<0.4,>=0.3; extra == "rag"
Requires-Dist: langchain-community<0.4,>=0.3; extra == "rag"
Requires-Dist: langchain-elasticsearch<=0.3.2,>=0.3.0; extra == "rag"
Requires-Dist: langchain-ibm<0.4,>=0.3; extra == "rag"
Requires-Dist: langgraph<0.7,>=0.2.40; extra == "rag"
Requires-Dist: langchain-chroma<=0.2.5,>=0.1.4; extra == "rag"
Requires-Dist: langchain-milvus<=0.2.1,>=0.1.8; extra == "rag"
Requires-Dist: grpcio>=1.54.3; extra == "rag"
Requires-Dist: python-docx<=1.2.0,>=1.1.2; extra == "rag"
Requires-Dist: python-pptx==1.0.2; extra == "rag"
Requires-Dist: pypdf>=4.2.0; extra == "rag"
Requires-Dist: beautifulsoup4<=4.13.5,>=4.12.3; extra == "rag"
Requires-Dist: markdown<=3.8.2,>=3.4.1; extra == "rag"
Requires-Dist: pyYAML>=5.1.2; extra == "rag"
Requires-Dist: scikit-learn>=1.3.0; extra == "rag"
Requires-Dist: openpyxl==3.1.5; extra == "rag"
Requires-Dist: langchain-db2<0.2,>=0.1; extra == "rag"
Provides-Extra: mcp
Requires-Dist: mcp<2.0,>=1.6.0; extra == "mcp"
